wydtools/__init__.py
wydtools/tool.py
wydtools/vol50000.py
wydtools/vol6_64.py
wydtools-0.8.8.dist-info/METADATA
wydtools-0.8.8.dist-info/WHEEL
wydtools-0.8.8.dist-info/top_level.txt
wydtools-0.8.8.dist-info/RECORD
