Metadata-Version: 2.1
Name: wydtools
Version: 0.8.8
Summary: Discharge voltage curves
Author: WYD
Author-email: wangyudong2018@ia.ac.cn
License: MIT Licence
Keywords: pip,wydtools
Platform: any
